arline_benchmarks/__init__.py
arline_benchmarks/config_parser/__init__.py
arline_benchmarks/config_parser/pipeline_config_parser.py
arline_benchmarks/engine/__init__.py
arline_benchmarks/engine/pipeline_engine.py
arline_benchmarks/metrics/__init__.py
arline_benchmarks/metrics/gate_chain_analyser.py
arline_benchmarks/pipeline/__init__.py
arline_benchmarks/pipeline/pipeline.py
arline_benchmarks/reports/__init__.py
arline_benchmarks/reports/kak_scheme.png
arline_benchmarks/reports/plot_benchmarks.py
arline_benchmarks/reports/results_logger.py
arline_benchmarks/strategies/__init__.py
arline_benchmarks/strategies/cirq_compression.py
arline_benchmarks/strategies/cirq_mapping.py
arline_benchmarks/strategies/qiskit_compression.py
arline_benchmarks/strategies/qiskit_mapping.py
arline_benchmarks/strategies/strategy.py
arline_benchmarks/strategies/target_analysis.py
arline_benchmarks/targets/__init__.py
arline_benchmarks/targets/target.py
arline_benchmarks-0.1.8.data/scripts/arline-benchmarks-runner
arline_benchmarks-0.1.8.data/scripts/arline-latex-report-generator
arline_benchmarks-0.1.8.dist-info/LICENSE
arline_benchmarks-0.1.8.dist-info/METADATA
arline_benchmarks-0.1.8.dist-info/WHEEL
arline_benchmarks-0.1.8.dist-info/top_level.txt
arline_benchmarks-0.1.8.dist-info/RECORD
