Metadata-Version: 2.1
Name: arline-benchmarks
Version: 0.1.8
Summary: Automated benchmarking platform for quantum compilers
Home-page: https://github.com/ArlineQ/arline_benchmarks
Author: Turation Ltd
Author-email: info@arline.io
License: GNU Affero General Public License v3 (AGPLv3)
Platform: UNKNOWN
Classifier: Programming Language :: Python :: 3
Classifier: License :: OSI Approved :: GNU Affero General Public License v3
Classifier: Operating System :: OS Independent
Requires-Python: >=3.6
Requires-Dist: numpy (>=1.18.3)
Requires-Dist: scipy (>=1.3.1)
Requires-Dist: jsonnet (>=0.15.0)
Requires-Dist: pylatex (>=1.3.1)
Requires-Dist: py-cpuinfo (>=5.0.0)
Requires-Dist: psutil (>=5.7.0)
Requires-Dist: pandas (>=0.25.3)
Requires-Dist: tqdm (>=4.46.0)
Requires-Dist: seaborn (>=0.10.1)
Requires-Dist: matplotlib (>=3.2.1)
Requires-Dist: cirq (~=0.6.0)
Requires-Dist: qiskit (~=0.18.0)
Requires-Dist: arline-quantum (~=0.1.8)
